mypackage/__init__.py
mypackage/__main__.py
mypackage/decorators.py
mypackage/descriptors.py
mypackage/generators.py
mypackage/iterators.py
mypackage/tests/__init__.py
voneska_mypackage-0.1.dist-info/METADATA
voneska_mypackage-0.1.dist-info/WHEEL
voneska_mypackage-0.1.dist-info/top_level.txt
voneska_mypackage-0.1.dist-info/RECORD
